Auto_process/Auto_python.py
Auto_process-1.0.1.dist-info/LICENSE.py
Auto_process-1.0.1.dist-info/METADATA
Auto_process-1.0.1.dist-info/WHEEL
Auto_process-1.0.1.dist-info/top_level.txt
Auto_process-1.0.1.dist-info/RECORD
