Metadata-Version: 2.1
Name: Auto-process
Version: 1.0.1
Summary: A Python package to get auto preprocess data.
Home-page: https://github.com/roshanfande/Auto-process
Author: Roshan Fande
License: MIT
Platform: UNKNOWN
Classifier: License :: OSI Approved :: MIT License
Classifier: Programming Language :: Python :: 3
Classifier: Programming Language :: Python :: 3.7
